alternat/__init__.py
alternat/version.py
alternat/collection/__init__.py
alternat/collection/collector.py
alternat/collection/apify/helper.js
alternat/collection/apify/main.js
alternat/collection/apify/main_single_page.js
alternat/generation/__init__.py
alternat/generation/config.py
alternat/generation/exceptions.py
alternat/generation/generator.py
alternat/generation/utilities.py
alternat/generation/base/__init__.py
alternat/generation/base/action_data_handler.py
alternat/generation/base/actions.py
alternat/generation/base/analyzer.py
alternat/generation/base/config.py
alternat/generation/google/__init__.py
alternat/generation/google/analyze.py
alternat/generation/google/config.py
alternat/generation/microsoft/__init__.py
alternat/generation/microsoft/analyze-local-image-ocr.py
alternat/generation/microsoft/analyze-local-image.py
alternat/generation/microsoft/analyze.py
alternat/generation/microsoft/config.py
alternat/generation/opensource/__init__.py
alternat/generation/opensource/analyze.py
alternat/generation/opensource/config.py
alternat/generation/opensource/models.py
alternat/generation/opensource/pytorchcaption.py
alternat/generation/rules/__init__.py
alternat/generation/rules/caption_handler.py
alternat/generation/rules/label_handler.py
alternat/generation/rules/ocr_cluster.py
alternat/generation/rules/ocr_handler.py
alternat-0.1.5.dist-info/LICENSE.txt
alternat-0.1.5.dist-info/METADATA
alternat-0.1.5.dist-info/WHEEL
alternat-0.1.5.dist-info/top_level.txt
alternat-0.1.5.dist-info/RECORD
