Metadata-Version: 2.1
Name: alternat
Version: 0.1.5
Summary: Alternat is a tool that automates alt text generation.
Home-page: https://github.com/keplerlab/alternat.git
Author: keplerlab
Author-email: keplerwaasi@gmail.com
License: UNKNOWN
Project-URL: Documentation, https://alternat.readthedocs.io
Project-URL: Source, https://github.com/keplerlab/alternat
Project-URL: Tracker, https://github.com/keplerlab/alternat/issues
Platform: UNKNOWN
Classifier: Programming Language :: Python :: 3
Classifier: License :: OSI Approved :: MIT License
Classifier: Operating System :: OS Independent
Requires-Python: >=3.6
Requires-Dist: pillow
Requires-Dist: torch (==1.4.0)
Requires-Dist: torchvision (==0.5.0)
Requires-Dist: google-cloud-vision (==1.0.0)
Requires-Dist: tldextract
Requires-Dist: easyocr
Requires-Dist: pyyaml
Requires-Dist: treelib
Requires-Dist: uvicorn
Requires-Dist: fastapi (==0.62.0)
Requires-Dist: typer (==0.3.2)
Requires-Dist: idna (<3,>=2.5)
Requires-Dist: gdown
